django_bitbucket_hook-1.2.6.dist-info/RECORD
django_bitbucket_hook-1.2.6.dist-info/DESCRIPTION.rst
django_bitbucket_hook-1.2.6.dist-info/metadata.json
django_bitbucket_hook-1.2.6.dist-info/WHEEL
django_bitbucket_hook-1.2.6.dist-info/METADATA
django_bitbucket_hook-1.2.6.dist-info/top_level.txt
django_bitbucket_hook/models.py
django_bitbucket_hook/admin.py
django_bitbucket_hook/__init__.py
django_bitbucket_hook/views.py
django_bitbucket_hook/urls.py
django_bitbucket_hook/tests.py
django_bitbucket_hook/migrations/0001_initial.py
django_bitbucket_hook/migrations/__init__.py
